aalink.cpython-310-aarch64-linux-gnu.so
aalink_aarch64-0.0.8.dist-info/entry_points.txt
aalink_aarch64-0.0.8.dist-info/WHEEL
aalink_aarch64-0.0.8.dist-info/METADATA
aalink_aarch64-0.0.8.dist-info/RECORD
aalink_aarch64-0.0.8.dist-info/licenses/LICENSE
