Metadata-Version: 2.1
Name: aalink-aarch64
Version: 0.0.8
Summary: Async Python interface for Ableton Link (aarch64)
Author-Email: Artem Popov <art@artfwo.net>
Classifier: Development Status :: 4 - Beta
Classifier: Intended Audience :: Developers
Classifier: License :: OSI Approved :: GNU General Public License v3 or later (GPLv3+)
Classifier: Programming Language :: Python :: 3
Classifier: Topic :: Artistic Software
Classifier: Topic :: Multimedia :: Sound/Audio
Classifier: Topic :: Software Development :: Libraries
Classifier: Topic :: System :: Networking
Project-URL: Homepage, https://github.com/ceebeel/aalink-aarch64
Requires-Python: >=3.8
License-File: LICENSE
